{
  "logger": {
    "level": "debug"  
  },
  "host": {
    "host": "172.25.0.120"
  },
  "emissary": {
    "protocol": "http",
    "hostname": "172.17.0.2",
    "apiKey": "<zap-api-key-here>",
    "apiFeedbackSpeed": 10000,
    "report": {
      "dir": "/var/log/purpleteam/outcomes/"
    }
  },
  "cucumber": {
    "tagExpression": "@app_scan",
    "timeout": 1800000
  },
  "results": {
    "dir": "/var/log/purpleteam/outcomes/"
  },
  "cloud": {
    "function": {
      "lambdaEndpoint": "http://172.25.0.1:3001"
    }
  }
}
